postgres_queue_artgas/__init__.py
postgres_queue_artgas/base.py
postgres_queue_artgas/db.py
postgres_queue_artgas/master.py
postgres_queue_artgas/worker.py
postgres_queue_artgas-1.0.0.dist-info/METADATA
postgres_queue_artgas-1.0.0.dist-info/WHEEL
postgres_queue_artgas-1.0.0.dist-info/top_level.txt
postgres_queue_artgas-1.0.0.dist-info/RECORD
