Metadata-Version: 2.1
Name: postgres_queue_artgas
Version: 1.0.0
Summary: Custom PostgreSQL Queue
Home-page: UNKNOWN
Author-email: kek@mail.ru
License: UNKNOWN
Platform: UNKNOWN
